dcr_core/__init__.py
dcr_core/__init__.pyi
dcr_core/cls_line_type_header_footer.py
dcr_core/cls_line_type_header_footer.pyi
dcr_core/cls_line_type_heading.py
dcr_core/cls_line_type_heading.pyi
dcr_core/cls_line_type_list_bullet.py
dcr_core/cls_line_type_list_bullet.pyi
dcr_core/cls_line_type_list_number.py
dcr_core/cls_line_type_list_number.pyi
dcr_core/cls_line_type_table.py
dcr_core/cls_line_type_table.pyi
dcr_core/cls_line_type_toc.py
dcr_core/cls_line_type_toc.pyi
dcr_core/cls_nlp_core.py
dcr_core/cls_nlp_core.pyi
dcr_core/cls_process.py
dcr_core/cls_process.pyi
dcr_core/cls_setup.py
dcr_core/cls_setup.pyi
dcr_core/cls_text_parser.py
dcr_core/cls_text_parser.pyi
dcr_core/cls_tokenizer_spacy.py
dcr_core/cls_tokenizer_spacy.pyi
dcr_core/core_glob.py
dcr_core/core_glob.pyi
dcr_core/core_utils.py
dcr_core/core_utils.pyi
dcr_core/py.typed
dcr_core/tetlib_py.pyd
dcr_core/tetlib_py.so
dcr_core/PDFlib/TET.py
dcr_core/PDFlib/__init__.py
dcr_core-0.9.7.dist-info/LICENSE
dcr_core-0.9.7.dist-info/METADATA
dcr_core-0.9.7.dist-info/WHEEL
dcr_core-0.9.7.dist-info/top_level.txt
dcr_core-0.9.7.dist-info/RECORD
