Metadata-Version: 2.1
Name: dcr-core
Version: 0.9.7
Summary: Document Content Recognition API
Author-email: Team Konnexions <info@konnexions.ch>
Maintainer-email: Team Konnexions <info@konnexions.ch>
Project-URL: Bug Tracker, https://github.com/KonnexionsGmbH/dcr-core/issues
Project-URL: Documentation, https://konnexionsgmbh.github.io/dcr-core/
Project-URL: Homepage, https://github.com/KonnexionsGmbH/dcr-core
Project-URL: Release Notes, https://konnexionsgmbh.github.io/dcr-core/release_notes/
Project-URL: Release History, https://konnexionsgmbh.github.io/dcr-core/release_history/
Keywords: Document Content Recognition,NLP,OCR
Classifier: Development Status :: 4 - Beta
Classifier: Environment :: Console
Classifier: Intended Audience :: Developers
Classifier: License :: Other/Proprietary License
Classifier: Natural Language :: English
Classifier: Operating System :: Microsoft :: Windows :: Windows 10
Classifier: Operating System :: POSIX :: Linux
Classifier: Programming Language :: Python :: 3.10
Classifier: Topic :: Text Processing
Classifier: Typing :: Typed
Requires-Python: >=3.10
License-File: LICENSE
